deetly/__init__.py
deetly/datapackage.py
deetly/echarts.py
deetly/error.py
deetly/utils.py
deetly/validator.py
deetly-0.0.27.dist-info/LICENSE
deetly-0.0.27.dist-info/WHEEL
deetly-0.0.27.dist-info/METADATA
deetly-0.0.27.dist-info/RECORD
